loadr/__init__.py
loadr/cli.py
pyproject.toml
loadr-0.1.7.dist-info/entry_points.txt
loadr-0.1.7.dist-info/WHEEL
loadr-0.1.7.dist-info/METADATA
loadr-0.1.7.dist-info/RECORD
