Metadata-Version: 2.1
Name: loadr
Version: 0.1.7
Summary: Simple tool to generate files based on Jinja2 templates and POST them to an API.
License: MIT
Author: Pascal Prins
Author-email: pascal.prins@foobar-it.com
Requires-Python: >=3.7,<4.0
Classifier: License :: OSI Approved :: MIT License
Classifier: Programming Language :: Python :: 3
Classifier: Programming Language :: Python :: 3.7
Classifier: Programming Language :: Python :: 3.8
Classifier: Programming Language :: Python :: 3.9
Requires-Dist: Faker (>=4.15.0,<5.0.0)
Requires-Dist: Jinja2 (>=2.11.2,<3.0.0)
Requires-Dist: PyYAML (>=5.3.1,<6.0.0)
Requires-Dist: click (>=7.1.2,<8.0.0)
Requires-Dist: requests (>=2.25.0,<3.0.0)
Requires-Dist: toml (>=0.10.2,<0.11.0)
